main.py
fusionaihub-0.1.0.dist-info/licenses/LICENSE
fusionaihub-0.1.0.dist-info/METADATA
fusionaihub-0.1.0.dist-info/WHEEL
fusionaihub-0.1.0.dist-info/top_level.txt
fusionaihub-0.1.0.dist-info/RECORD
