Metadata-Version: 2.4
Name: fusionaihub
Version: 0.1.0
Summary: Placeholder release
Requires-Python: >=3.13
License-File: LICENSE
Requires-Dist: numpy
Dynamic: license-file
